{
    "Amp": [
        {
            "param0": "Amp",
            "param1": "Amp",
            "mode0": "1",
            "mode1": "1",
            "center": -0.014300449813054653,
            "width": 0.037077545517221075,
            "polyfit": [
                363.7152928269992,
                10.402584582625957,
                -1.8701284556896285e-06
            ]
        },
        {
            "param0": "Amp",
            "param1": "Amp",
            "mode0": "2",
            "mode1": "2",
            "center": -0.005844891422680042,
            "width": 0.037128823521653996,
            "polyfit": [
                362.73086175798534,
                4.240245005261177,
                -1.1356914661591602e-06
            ]
        },
        {
            "param0": "Amp",
            "param1": "Amp",
            "mode0": "3",
            "mode1": "3",
            "center": -0.020877527070547998,
            "width": 0.15996490988615092,
            "polyfit": [
                19.53992274417772,
                0.8158905320959737,
                0.2599367669738308
            ]
        },
        {
            "param0": "Amp",
            "param1": "Amp",
            "mode0": "4",
            "mode1": "4",
            "center": 0.0498006527917594,
            "width": 0.05771602610200401,
            "polyfit": [
                150.1022096910636,
                -14.950376056201042,
                0.25790389596068136
            ]
        },
        {
            "param0": "Amp",
            "param1": "Amp",
            "mode0": "5",
            "mode1": "5",
            "center": 0.0007368898879243823,
            "width": 0.23136417020318634,
            "polyfit": [
                9.340674785184495,
                -0.013766097591185411,
                0.04868554389504015
            ]
        },
        {
            "param0": "Amp",
            "param1": "Amp",
            "mode0": "6",
            "mode1": "6",
            "center": -0.017044325588837984,
            "width": 0.11899381084434232,
            "polyfit": [
                35.31245189245541,
                1.2037538547903759,
                -0.07833143595206578
            ]
        },
        {
            "param0": "Amp",
            "param1": "Amp",
            "mode0": "7",
            "mode1": "7",
            "center": 0.013211732073090818,
            "width": 0.08161505709961939,
            "polyfit": [
                75.06458735970207,
                -1.983466432747007,
                -0.08090019437168329
            ]
        },
        {
            "param0": "Amp",
            "param1": "Amp",
            "mode0": "8",
            "mode1": "8",
            "center": -0.06254876127154643,
            "width": 0.12266119051380003,
            "polyfit": [
                33.231937480944794,
                4.157233048173144,
                0.13211443480503218
            ]
        },
        {
            "param0": "Amp",
            "param1": "Amp",
            "mode0": "9",
            "mode1": "9",
            "center": -0.02309946018674279,
            "width": 0.10640306665346684,
            "polyfit": [
                44.163983109006644,
                2.04032833902896,
                0.005654233114945602
            ]
        },
        {
            "param0": "Amp",
            "param1": "Amp",
            "mode0": "0",
            "mode1": "0",
            "center": -0.0008687513880503315,
            "width": 0.002544525054418819,
            "polyfit": [
                77225.28863843674,
                134.17915339445884,
                -1.2903223188046489
            ]
        }
    ],
    "Phs": [
        {
            "param0": "Phs",
            "param1": "Phs",
            "mode0": "1",
            "mode1": "1",
            "center": 0.020767965885535148,
            "width": 0.0426563248668848,
            "polyfit": [
                274.80142849520485,
                -11.414133384569482,
                -0.09982295484273528
            ]
        },
        {
            "param0": "Phs",
            "param1": "Phs",
            "mode0": "2",
            "mode1": "2",
            "center": -0.011071880693352623,
            "width": 0.03260505761318465,
            "polyfit": [
                470.410459151273,
                10.416656961256244,
                1.2727057521950618e-06
            ]
        },
        {
            "param0": "Phs",
            "param1": "Phs",
            "mode0": "3",
            "mode1": "3",
            "center": -0.07856452846501275,
            "width": 0.16776926150261162,
            "polyfit": [
                17.76418259327292,
                2.7912692580137484,
                0.14029063757649254
            ]
        },
        {
            "param0": "Phs",
            "param1": "Phs",
            "mode0": "4",
            "mode1": "4",
            "center": 0.021075562516239252,
            "width": 0.05472759657930509,
            "polyfit": [
                166.9493433738084,
                -7.0371026466395845,
                0.07981106857916274
            ]
        },
        {
            "param0": "Phs",
            "param1": "Phs",
            "mode0": "5",
            "mode1": "5",
            "center": 0.14202985540452875,
            "width": 0.2358250730295634,
            "polyfit": [
                8.99066249721547,
                -2.553884988940865,
                0.184346921014767
            ]
        },
        {
            "param0": "Phs",
            "param1": "Phs",
            "mode0": "6",
            "mode1": "6",
            "center": -0.010792876311375849,
            "width": 0.11728326847639359,
            "polyfit": [
                36.34967191117856,
                0.7846350257928864,
                0.17839170364510618
            ]
        },
        {
            "param0": "Phs",
            "param1": "Phs",
            "mode0": "7",
            "mode1": "7",
            "center": -0.04021136713806965,
            "width": 0.08292631584520557,
            "polyfit": [
                72.70952161208993,
                5.847498535954316,
                0.0199447280685407
            ]
        },
        {
            "param0": "Phs",
            "param1": "Phs",
            "mode0": "8",
            "mode1": "8",
            "center": 0.004474932597088481,
            "width": 0.13601344460292825,
            "polyfit": [
                27.027529057605847,
                -0.24189274159727306,
                -0.1197372882478362
            ]
        },
        {
            "param0": "Phs",
            "param1": "Phs",
            "mode0": "9",
            "mode1": "9",
            "center": -0.01441479317940874,
            "width": 0.1114793318689051,
            "polyfit": [
                40.23292324666005,
                1.1598985352072613,
                0.06078600193226491
            ]
        }
    ],
    "AmpPhs": [
        {
            "param0": "Amp",
            "param1": "Phs",
            "mode0": "0",
            "mode1": "1",
            "center": 0.2019297873602524,
            "width": 0.7651779334151954,
            "polyfit": [
                0.8539756048161247,
                -0.344886224582726,
                0.3932610741692013
            ]
        },
        {
            "param0": "Amp",
            "param1": "Phs",
            "mode0": "0",
            "mode1": "2",
            "center": 0.09582863555240007,
            "width": 0.8285246955834633,
            "polyfit": [
                0.7283835473532357,
                -0.13960000300335512,
                0.20107971102860736
            ]
        },
        {
            "param0": "Amp",
            "param1": "Phs",
            "mode0": "0",
            "mode1": "3",
            "center": -0.060987533960728105,
            "width": 1.2194734028390726,
            "polyfit": [
                0.33622145656318,
                0.04101063500094482,
                -0.001609184873160162
            ]
        },
        {
            "param0": "Amp",
            "param1": "Phs",
            "mode0": "0",
            "mode1": "4",
            "center": 0.15309728330205924,
            "width": 0.9984838837083385,
            "polyfit": [
                0.5015206730651541,
                -0.15356290513219067,
                0.13205328430187332
            ]
        },
        {
            "param0": "Amp",
            "param1": "Phs",
            "mode0": "1",
            "mode1": "1",
            "center": 0.4102824246776079,
            "width": 1.2008253696674207,
            "polyfit": [
                0.3467451502952363,
                -0.2845268820166622,
                0.09930861166020674
            ]
        },
        {
            "param0": "Amp",
            "param1": "Phs",
            "mode0": "1",
            "mode1": "2",
            "center": 0.34531995602979415,
            "width": 0.8660603601758399,
            "polyfit": [
                0.66661447890455,
                -0.46039056508828663,
                0.41139623976412737
            ]
        },
        {
            "param0": "Amp",
            "param1": "Phs",
            "mode0": "1",
            "mode1": "3",
            "center": 0.08321550974868325,
            "width": 1.1179802762031146,
            "polyfit": [
                0.40003858183917756,
                -0.066578829013775,
                0.24523301377764706
            ]
        },
        {
            "param0": "Amp",
            "param1": "Phs",
            "mode0": "1",
            "mode1": "4",
            "center": 0.23396454010613024,
            "width": 1.0155069593119304,
            "polyfit": [
                0.48484727811047673,
                -0.22687414088965344,
                -0.012628975914184307
            ]
        },
        {
            "param0": "Amp",
            "param1": "Phs",
            "mode0": "2",
            "mode1": "1",
            "center": 0.06320401052668052,
            "width": 0.9422728479296474,
            "polyfit": [
                0.5631414743730396,
                -0.07118559934856797,
                -0.04150208434748194
            ]
        },
        {
            "param0": "Amp",
            "param1": "Phs",
            "mode0": "2",
            "mode1": "2",
            "center": -0.17209467555523184,
            "width": 0.9628898387265437,
            "polyfit": [
                0.5392832236636145,
                0.1856155428175385,
                -0.17106329702608697
            ]
        },
        {
            "param0": "Amp",
            "param1": "Phs",
            "mode0": "2",
            "mode1": "3",
            "center": -0.06135009294290471,
            "width": 1.0649465069689141,
            "polyfit": [
                0.4408739415684285,
                0.05409531458265566,
                0.006770473140726346
            ]
        },
        {
            "param0": "Amp",
            "param1": "Phs",
            "mode0": "2",
            "mode1": "4",
            "center": -0.012570463044191795,
            "width": 1.0167923739683755,
            "polyfit": [
                0.48362173634378025,
                0.012158698328154714,
                0.03614043281055188
            ]
        },
        {
            "param0": "Amp",
            "param1": "Phs",
            "mode0": "3",
            "mode1": "1",
            "center": 0.33369308364834455,
            "width": 1.2401699700695998,
            "polyfit": [
                0.3250931737924733,
                -0.21696268727167523,
                0.08487322721109139
            ]
        },
        {
            "param0": "Amp",
            "param1": "Phs",
            "mode0": "3",
            "mode1": "2",
            "center": 0.13703623178875837,
            "width": 0.8527045016326593,
            "polyfit": [
                0.687658829468788,
                -0.18846834949334218,
                0.06771663038506201
            ]
        },
        {
            "param0": "Amp",
            "param1": "Phs",
            "mode0": "3",
            "mode1": "3",
            "center": 0.14981914451039927,
            "width": 1.1421805370478353,
            "polyfit": [
                0.3832666311490255,
                -0.11484135759625948,
                0.07358515807894712
            ]
        },
        {
            "param0": "Amp",
            "param1": "Phs",
            "mode0": "3",
            "mode1": "4",
            "center": -0.15441301014054773,
            "width": 0.9857039153244868,
            "polyfit": [
                0.5146086158840534,
                0.15892453084583513,
                0.07701765925099634
            ]
        },
        {
            "param0": "Amp",
            "param1": "Phs",
            "mode0": "4",
            "mode1": "1",
            "center": -0.16182062227638075,
            "width": 0.9394516281146046,
            "polyfit": [
                0.5665286982921969,
                0.1833520529901425,
                0.2301943049116103
            ]
        },
        {
            "param0": "Amp",
            "param1": "Phs",
            "mode0": "4",
            "mode1": "2",
            "center": -0.11087554130225045,
            "width": 0.9904466090672509,
            "polyfit": [
                0.5096929630918893,
                0.11302496636152237,
                0.15101459876697543
            ]
        },
        {
            "param0": "Amp",
            "param1": "Phs",
            "mode0": "4",
            "mode1": "3",
            "center": -0.5120050404234616,
            "width": 0.9842636314851206,
            "polyfit": [
                0.5161158014824058,
                0.5285077836023729,
                0.6237613952185109
            ]
        },
        {
            "param0": "Amp",
            "param1": "Phs",
            "mode0": "4",
            "mode1": "4",
            "center": -0.26002105867998837,
            "width": 0.9193242887399649,
            "polyfit": [
                0.5916060602692547,
                0.3076600682254172,
                -0.1132483216642822
            ]
        },
        {
            "param0": "Amp",
            "param1": "Amp",
            "mode0": "1",
            "mode1": "0",
            "center": 0.4344959796054184,
            "width": 0.8947036243500612,
            "polyfit": [
                0.6246143253300223,
                -0.542784826319691,
                0.1063499696993199
            ]
        },
        {
            "param0": "Amp",
            "param1": "Amp",
            "mode0": "2",
            "mode1": "0",
            "center": 0.1634975124888863,
            "width": 0.8403664560198064,
            "polyfit": [
                0.7079989132263252,
                -0.2315121223146781,
                -0.1729637459706613
            ]
        },
        {
            "param0": "Amp",
            "param1": "Amp",
            "mode0": "2",
            "mode1": "1",
            "center": -0.05032930352730821,
            "width": 1.438361470513813,
            "polyfit": [
                0.24167629704580623,
                0.024326799418748563,
                -0.0007224249052146886
            ]
        },
        {
            "param0": "Amp",
            "param1": "Amp",
            "mode0": "3",
            "mode1": "0",
            "center": 0.14676741860734355,
            "width": 1.0873346545367388,
            "polyfit": [
                0.42290621659500355,
                -0.12413770744529358,
                -0.3603893435464537
            ]
        },
        {
            "param0": "Amp",
            "param1": "Amp",
            "mode0": "3",
            "mode1": "1",
            "center": 0.15935960549500985,
            "width": 1.193095902979397,
            "polyfit": [
                0.3512527638661862,
                -0.11195100375749457,
                0.002731077018588502
            ]
        },
        {
            "param0": "Amp",
            "param1": "Amp",
            "mode0": "3",
            "mode1": "2",
            "center": -0.1693675362906728,
            "width": 1.2037787196550296,
            "polyfit": [
                0.34504576014160554,
                0.11687910060545231,
                0.10046326850846155
            ]
        },
        {
            "param0": "Amp",
            "param1": "Amp",
            "mode0": "4",
            "mode1": "0",
            "center": -0.16374793480184321,
            "width": 0.8298263271266808,
            "polyfit": [
                0.7260986067213349,
                0.23779429462622867,
                0.13032119775540188
            ]
        },
        {
            "param0": "Amp",
            "param1": "Amp",
            "mode0": "4",
            "mode1": "1",
            "center": -0.11867384778884674,
            "width": 0.8331946249918971,
            "polyfit": [
                0.7202397614893515,
                0.17094724765292516,
                -0.17665173531172207
            ]
        },
        {
            "param0": "Amp",
            "param1": "Amp",
            "mode0": "4",
            "mode1": "2",
            "center": 0.1292636314300003,
            "width": 1.1876981556699973,
            "polyfit": [
                0.35445275952428307,
                -0.09163570173298692,
                0.02867075569690049
            ]
        },
        {
            "param0": "Amp",
            "param1": "Amp",
            "mode0": "4",
            "mode1": "3",
            "center": 0.4233066580543916,
            "width": 1.3787274667336722,
            "polyfit": [
                0.2630350363959136,
                -0.22268896441593888,
                0.1510465637402325
            ]
        },
        {
            "param0": "Phs",
            "param1": "Phs",
            "mode0": "2",
            "mode1": "1",
            "center": 0.22744170309686526,
            "width": 1.3101383659426298,
            "polyfit": [
                0.2912968904682172,
                -0.13250612174982468,
                0.07032950828183022
            ]
        },
        {
            "param0": "Phs",
            "param1": "Phs",
            "mode0": "3",
            "mode1": "1",
            "center": 0.18818033107965873,
            "width": 1.1528074721966568,
            "polyfit": [
                0.37623271031707145,
                -0.14159919198092769,
                0.010133960301771787
            ]
        },
        {
            "param0": "Phs",
            "param1": "Phs",
            "mode0": "3",
            "mode1": "2",
            "center": -0.2692220011943507,
            "width": 1.3839798230191631,
            "polyfit": [
                0.26104210653838855,
                0.14055655663650773,
                0.11154655932657348
            ]
        },
        {
            "param0": "Phs",
            "param1": "Phs",
            "mode0": "4",
            "mode1": "1",
            "center": 0.031352646723367926,
            "width": 0.9516211673900241,
            "polyfit": [
                0.5521306159607623,
                -0.034621512294746616,
                -0.11079237482881436
            ]
        },
        {
            "param0": "Phs",
            "param1": "Phs",
            "mode0": "4",
            "mode1": "2",
            "center": -0.002013400194460783,
            "width": 1.085191119718432,
            "polyfit": [
                0.42457814850085135,
                0.0017096914535108265,
                -0.05242120465275646
            ]
        },
        {
            "param0": "Phs",
            "param1": "Phs",
            "mode0": "4",
            "mode1": "3",
            "center": 0.06810688982556448,
            "width": 1.3206147753943018,
            "polyfit": [
                0.2866934574808549,
                -0.03905159944471748,
                -0.06468755940866648
            ]
        }
    ]
}